{"PassengerId":61,"Survived":0,"Pclass":3,"Name":"Sirayanian, Mr. Orsen","Sex":"male","Age":22.0,"SibSp":0,"Parch":0,"Ticket":"2669","Fare":7.2292,"Cabin":null,"Embarked":"C","event_time":"2026-04-28 22:32:07","source":"SIMULATED_DEVICE"}
{"PassengerId":62,"Survived":1,"Pclass":1,"Name":"Icard, Miss. Amelie","Sex":"female","Age":38.0,"SibSp":0,"Parch":0,"Ticket":"113572","Fare":80.0,"Cabin":"B28","Embarked":null,"event_time":"2026-04-28 22:32:07","source":"SIMULATED_DEVICE"}
{"PassengerId":63,"Survived":0,"Pclass":1,"Name":"Harris, Mr. Henry Birkhardt","Sex":"male","Age":45.0,"SibSp":1,"Parch":0,"Ticket":"36973","Fare":83.475,"Cabin":"C83","Embarked":"S","event_time":"2026-04-28 22:32:07","source":"SIMULATED_DEVICE"}
{"PassengerId":64,"Survived":0,"Pclass":3,"Name":"Skoog, Master. Harald","Sex":"male","Age":4.0,"SibSp":3,"Parch":2,"Ticket":"347088","Fare":27.9,"Cabin":null,"Embarked":"S","event_time":"2026-04-28 22:32:07","source":"SIMULATED_DEVICE"}
{"PassengerId":65,"Survived":0,"Pclass":1,"Name":"Stewart, Mr. Albert A","Sex":"male","Age":null,"SibSp":0,"Parch":0,"Ticket":"PC 17605","Fare":27.7208,"Cabin":null,"Embarked":"C","event_time":"2026-04-28 22:32:07","source":"SIMULATED_DEVICE"}
{"PassengerId":66,"Survived":1,"Pclass":3,"Name":"Moubarek, Master. Gerios","Sex":"male","Age":null,"SibSp":1,"Parch":1,"Ticket":"2661","Fare":15.2458,"Cabin":null,"Embarked":"C","event_time":"2026-04-28 22:32:07","source":"SIMULATED_DEVICE"}
{"PassengerId":67,"Survived":1,"Pclass":2,"Name":"Nye, Mrs. (Elizabeth Ramell)","Sex":"female","Age":29.0,"SibSp":0,"Parch":0,"Ticket":"C.A. 29395","Fare":10.5,"Cabin":"F33","Embarked":"S","event_time":"2026-04-28 22:32:07","source":"SIMULATED_DEVICE"}
{"PassengerId":68,"Survived":0,"Pclass":3,"Name":"Crease, Mr. Ernest James","Sex":"male","Age":19.0,"SibSp":0,"Parch":0,"Ticket":"S.P. 3464","Fare":8.1583,"Cabin":null,"Embarked":"S","event_time":"2026-04-28 22:32:07","source":"SIMULATED_DEVICE"}
{"PassengerId":69,"Survived":1,"Pclass":3,"Name":"Andersson, Miss. Erna Alexandra","Sex":"female","Age":17.0,"SibSp":4,"Parch":2,"Ticket":"3101281","Fare":7.925,"Cabin":null,"Embarked":"S","event_time":"2026-04-28 22:32:07","source":"SIMULATED_DEVICE"}
{"PassengerId":70,"Survived":0,"Pclass":3,"Name":"Kink, Mr. Vincenz","Sex":"male","Age":26.0,"SibSp":2,"Parch":0,"Ticket":"315151","Fare":8.6625,"Cabin":null,"Embarked":"S","event_time":"2026-04-28 22:32:07","source":"SIMULATED_DEVICE"}
